agentutil/__init__.py
agentutil/agent.py
agentutil/helper/__init__.py
agentutil/helper/mongo_client.py
agentutil/helper/publisher.py
agentutil/helper/sql_client.py
agentutil/models/__init__.py
agentutil/models/blocked_sites.py
agentutil/models/news.py
agentutil/utils/__init__.py
agentutil/utils/agentAssistant.py
agentutil/utils/sjAssistant.py
agentutil-0.2.0.dist-info/METADATA
agentutil-0.2.0.dist-info/WHEEL
agentutil-0.2.0.dist-info/top_level.txt
agentutil-0.2.0.dist-info/RECORD
