Metadata-Version: 2.4
Name: agentutil
Version: 0.2.0
Summary: Basic classes and utils for developing agents
Requires-Python: >=3.12
Requires-Dist: beautifulsoup4==4.13.4
Requires-Dist: django>=5.2.1
Requires-Dist: flake8>=7.2.0
Requires-Dist: langchain>=0.3.25
Requires-Dist: pydantic>=2.11.4
Requires-Dist: pymongo==4.13.0
Requires-Dist: pymysql>=1.1.1
Requires-Dist: python-dotenv>=1.1.0
Requires-Dist: pytz>=2025.2
Requires-Dist: selenium==4.31.0
Requires-Dist: sqlalchemy>=2.0.41
Requires-Dist: webdriver-manager==4.0.2
